CHANGELOG
LICENSE
MANIFEST.in
README
README.rst
setup.cfg
setup.py
test_requirements.txt
signalslot/__init__.py
signalslot/exceptions.py
signalslot/signal.py
signalslot/slot.py
signalslot/tests.py
signalslot.egg-info/PKG-INFO
signalslot.egg-info/SOURCES.txt
signalslot.egg-info/dependency_links.txt
signalslot.egg-info/requires.txt
signalslot.egg-info/top_level.txt
signalslot/contrib/__init__.py
signalslot/contrib/task/__init__.py
signalslot/contrib/task/task.py
signalslot/contrib/task/test.py