Metadata-Version: 2.1
Name: signalslot
Version: 0.2.0
Summary: Simple Signal/Slot implementation
Home-page: https://github.com/numergy/signalslot
License: MIT
Keywords: signal slot
Classifier: Development Status :: 5 - Production/Stable
Classifier: Intended Audience :: Developers
Classifier: License :: OSI Approved :: MIT License
Classifier: Operating System :: OS Independent
Classifier: Programming Language :: Python
Classifier: Programming Language :: Python :: 2
Classifier: Programming Language :: Python :: 3
Classifier: Topic :: Software Development :: Libraries :: Python Modules
Requires-Python: >=3.4
License-File: LICENSE
